{
  "title": "Traveling with children",
  "slug": "TravelingWithChildren",
  "date": "2022-01-12T14:12:03.284Z",
  "description": "A check list for traveling with children",
  "source": "https://www.checkli.com/checklists/perfectlyplanned/the-survivors-guide-to-traveling-with-children",
  "tags": [
    "travel",
    "hard",
    "children"
  ],
  "abstract": "Basic check list which can be used just before heading to a trip with children.",
  "items": [
    "Favorite pillow and blanket",
    "Favorite snuggly toy or lovie",
    "Plenty of snacks ",
    "Travel games",
    "iPad or tablet so they can watch movies",
    "Kid friendly app games for your iPad or Tablet",
    "Charger",
    "Crayons",
    "Coloring books",
    "Activity books",
    "Extra coat",
    "Extra socks",
    "Extra shoes",
    "Winter wear",
    "Favorite story books ",
    "Audio books",
    "Pack a backpack with their favorite toys",
    "Mini cooler with extra drinks for the kids",
    "Napkins and wipes",
    "First aide kit",
    "Teach your family some good ole' family road trip games"
  ]
}